{"name":"zijinling3_tx","SubTexture":[{"name":"png/ball1","x":219,"width":103,"y":889,"height":96},{"name":"png/ball2","x":3982,"width":111,"y":465,"height":103},{"name":"png/ball3","x":3982,"width":112,"y":570,"height":100},{"name":"png/ball4","x":3843,"width":139,"y":1121,"height":111},{"name":"png/ball5","x":2126,"width":135,"y":1128,"height":110},{"name":"png/ball6","x":1046,"width":144,"y":1107,"height":120},{"name":"png/ball7","x":2944,"width":147,"y":1102,"height":119},{"name":"png/yan1","x":4013,"width":71,"y":0,"height":62},{"name":"png/yan2","x":2253,"width":88,"y":342,"height":73},{"name":"png/yan3","x":1979,"width":145,"y":1128,"height":104},{"name":"png/yan4","x":1192,"width":150,"y":1107,"height":108},{"name":"png/yan5","x":3920,"width":170,"y":877,"height":121},{"name":"png/yan6","x":3920,"width":171,"y":1000,"height":119},{"name":"png/yan7","x":410,"width":194,"y":1002,"height":143},{"name":"png/yan8","x":1451,"width":194,"y":990,"height":147},{"name":"png/yan9","x":1119,"width":197,"y":953,"height":152},{"name":"png/yan10","x":2341,"width":203,"y":897,"height":150},{"name":"png/yan11","x":843,"width":201,"y":984,"height":146},{"name":"png/yan12","x":2955,"width":200,"y":947,"height":153},{"name":"png/yan13","x":2134,"width":205,"y":897,"height":164},{"name":"png/yan14","x":3486,"width":215,"y":873,"height":170},{"name":"png/yan15","x":3703,"width":215,"y":873,"height":170},{"name":"png/yan16","x":219,"width":189,"y":1002,"height":152},{"name":"png/yan17","x":1647,"width":183,"y":990,"height":148},{"name":"png/yan18","x":752,"width":134,"y":1132,"height":108},{"name":"png/mars1","x":3968,"width":126,"y":779,"height":96},{"name":"png/mars2","x":3157,"width":153,"y":1099,"height":116},{"name":"png/mars3","x":2546,"width":172,"y":1045,"height":114},{"name":"png/mars4","x":2568,"width":173,"y":740,"height":123},{"name":"png/mars5","x":2568,"width":175,"y":606,"height":132},{"name":"png/mars6","x":2341,"width":149,"y":1049,"height":129},{"name":"png/mars7","x":1832,"width":145,"y":1089,"height":125},{"name":"png/mars8","x":3982,"width":101,"y":672,"height":105},{"name":"重复项目文件夹/sprite 63","x":2556,"width":178,"y":865,"height":178},{"name":"重复项目文件夹/sprite 68","x":606,"width":145,"y":1115,"height":113},{"name":"png/fire1","x":971,"width":284,"y":325,"height":217},{"name":"png/fire2","x":1610,"width":297,"y":311,"height":239},{"name":"png/fire3","x":1287,"width":279,"y":314,"height":253},{"name":"png/fire4","x":3697,"width":314,"y":0,"height":290},{"name":"png/fire5","x":333,"width":321,"y":0,"height":318},{"name":"png/fire6","x":0,"width":331,"y":0,"height":327},{"name":"png/fire7","x":656,"width":313,"y":0,"height":325},{"name":"png/fire8","x":971,"width":314,"y":0,"height":323},{"name":"png/fire9","x":1287,"width":321,"y":0,"height":312},{"name":"png/fire10","x":1610,"width":311,"y":0,"height":309},{"name":"png/fire11","x":1286,"width":270,"y":569,"height":201},{"name":"png/fire12","x":1318,"width":131,"y":953,"height":152},{"name":"png/yanchen1-1.png","x":888,"width":145,"y":1132,"height":60},{"name":"png/yanchen2-1.png","x":2720,"width":173,"y":1116,"height":81},{"name":"png/yanchen3-1.png","x":843,"width":274,"y":900,"height":82},{"name":"png/yanchen4-1.png","x":1467,"width":293,"y":927,"height":61},{"name":"png/yanchen5-1.png","x":3157,"width":288,"y":947,"height":63},{"name":"png/yanchen6-1.png","x":1833,"width":299,"y":769,"height":139},{"name":"png/yanchen7-1.png","x":0,"width":314,"y":746,"height":141},{"name":"png/yanchen8-1.png","x":3582,"width":398,"y":465,"height":162},{"name":"png/yanchen9-1.png","x":2769,"width":408,"y":338,"height":164},{"name":"png/yanchen10-1.png","x":1923,"width":428,"y":174,"height":166},{"name":"png/yanchen11-1.png","x":2343,"width":400,"y":350,"height":167},{"name":"png/yanchen12-1.png","x":3179,"width":401,"y":338,"height":170},{"name":"png/yanchen13-1.png","x":3661,"width":408,"y":292,"height":171},{"name":"png/yanchen14-1.png","x":2353,"width":414,"y":174,"height":174},{"name":"png/yanchen15-1.png","x":3231,"width":428,"y":161,"height":175},{"name":"png/yanchen16-1.png","x":2801,"width":428,"y":161,"height":175},{"name":"png/yanchen17-1.png","x":1923,"width":437,"y":0,"height":172},{"name":"png/yanchen18-1.png","x":2362,"width":437,"y":0,"height":172},{"name":"png/yanchen19-1.png","x":2801,"width":446,"y":0,"height":159},{"name":"png/yanchen20-1.png","x":3249,"width":446,"y":0,"height":159},{"name":"png/yanchen21-1.png","x":3082,"width":436,"y":688,"height":88},{"name":"png/yanchen22-1.png","x":3544,"width":436,"y":629,"height":88},{"name":"png/yanchen23-1.png","x":3504,"width":438,"y":797,"height":74},{"name":"png/yanchen24-1.png","x":3064,"width":438,"y":778,"height":75},{"name":"png/yanchen25-1.png","x":3520,"width":446,"y":719,"height":76},{"name":"png/yanchen26-1.png","x":3082,"width":460,"y":603,"height":83},{"name":"png/yanchen27-1.png","x":2253,"width":461,"y":519,"height":85},{"name":"png/yanchen28-1.png","x":3082,"width":461,"y":510,"height":91},{"name":"png/yanchen29-1.png","x":2134,"width":420,"y":805,"height":90},{"name":"png/yanchen30-1.png","x":3064,"width":420,"y":855,"height":90},{"name":"png/yanchen31-1.png","x":1833,"width":265,"y":910,"height":90},{"name":"png/yanchen32-1.png","x":324,"width":265,"y":910,"height":90},{"name":"png/yanchen33-1.png","x":1832,"width":246,"y":1002,"height":85},{"name":"png/yanchen34-1.png","x":3157,"width":246,"y":1012,"height":85},{"name":"png/yanchen35-1.png","x":606,"width":222,"y":1050,"height":63},{"name":"png/yanchen36-1.png","x":2720,"width":222,"y":1051,"height":63},{"name":"png/yanchen37-1.png","x":2080,"width":222,"y":1063,"height":63},{"name":"png/sha1-1.png","x":331,"width":291,"y":717,"height":191},{"name":"png/sha2-1.png","x":655,"width":298,"y":327,"height":195},{"name":"png/sha3-1.png","x":1558,"width":273,"y":751,"height":174},{"name":"png/sha4-1.png","x":964,"width":282,"y":722,"height":176},{"name":"png/sha5-1.png","x":649,"width":313,"y":711,"height":176},{"name":"png/sha6-1.png","x":970,"width":314,"y":544,"height":176},{"name":"png/sha7-1.png","x":331,"width":316,"y":517,"height":198},{"name":"png/sha8-1.png","x":2745,"width":317,"y":703,"height":185},{"name":"png/sha9-1.png","x":649,"width":319,"y":524,"height":185},{"name":"png/sha10-1.png","x":333,"width":320,"y":320,"height":195},{"name":"png/sha11-1.png","x":1903,"width":332,"y":570,"height":197},{"name":"png/sha12-1.png","x":1568,"width":333,"y":552,"height":197},{"name":"png/sha13-1.png","x":2745,"width":335,"y":504,"height":197},{"name":"png/sha14-1.png","x":0,"width":329,"y":329,"height":216},{"name":"png/sha15-1.png","x":0,"width":329,"y":547,"height":197},{"name":"png/sha16-1.png","x":2237,"width":329,"y":606,"height":197},{"name":"png/sha17-1.png","x":1909,"width":342,"y":342,"height":226},{"name":"png/sha18-1.png","x":0,"width":217,"y":889,"height":159},{"name":"png/sha19-1.png","x":2736,"width":217,"y":890,"height":159},{"name":"png/sha20-1.png","x":624,"width":217,"y":889,"height":159},{"name":"png/sha21-1.png","x":1248,"width":217,"y":772,"height":179},{"name":"png/sha22-1.png","x":0,"width":217,"y":1050,"height":108},{"name":"png/sha23-1.png","x":3624,"width":217,"y":1045,"height":108},{"name":"png/sha24-1.png","x":3405,"width":217,"y":1045,"height":108}],"imagePath":"texture.png"}