{"name":"buff_shengguang","SubTexture":[{"name":"ziyuan/shengg1","x":373,"width":47,"y":302,"height":27},{"name":"ziyuan/shengg2","x":60,"width":38,"y":309,"height":22},{"name":"ziyuan/guangm1","x":121,"width":56,"y":0,"height":310},{"name":"ziyuan/guangm2","x":0,"width":58,"y":0,"height":310},{"name":"ziyuan/guangm3","x":60,"width":59,"y":0,"height":307},{"name":"ziyuan/guangm4","x":373,"width":58,"y":0,"height":300},{"name":"ziyuan/guangm5","x":433,"width":59,"y":293,"height":295},{"name":"ziyuan/guangm6","x":179,"width":63,"y":0,"height":299},{"name":"ziyuan/guangm7","x":309,"width":62,"y":0,"height":298},{"name":"ziyuan/guangm8","x":244,"width":63,"y":0,"height":297},{"name":"ziyuan/guangm9","x":433,"width":63,"y":0,"height":291},{"name":"ziyuan/guangm10","x":244,"width":63,"y":299,"height":290},{"name":"ziyuan/guangm11","x":179,"width":63,"y":301,"height":290},{"name":"ziyuan/guangm12","x":100,"width":61,"y":312,"height":289},{"name":"ziyuan/guangm13","x":309,"width":62,"y":300,"height":289}],"imagePath":"texture.png"}