{"name":"jinrangjiasha1_tx","SubTexture":[{"name":"ziyuan/masak1","x":135,"width":132,"y":0,"height":128},{"name":"ziyuan/masak2","x":0,"width":133,"y":0,"height":129},{"name":"ziyuan/masak3","x":397,"width":111,"y":0,"height":111},{"name":"ziyuan/masak4","x":269,"width":126,"y":0,"height":133},{"name":"ziyuan/masak5","x":0,"width":124,"y":131,"height":127},{"name":"ziyuan/masak6","x":135,"width":126,"y":130,"height":129},{"name":"ziyuan/masak7","x":263,"width":125,"y":135,"height":124},{"name":"ziyuan/masak8","x":0,"width":121,"y":260,"height":126},{"name":"ziyuan/masak9","x":390,"width":116,"y":225,"height":113},{"name":"ziyuan/masak10","x":241,"width":101,"y":261,"height":101},{"name":"ziyuan/masak11","x":241,"width":86,"y":364,"height":86},{"name":"ziyuan/masak12","x":123,"width":70,"y":371,"height":66},{"name":"ziyuan/masak13","x":463,"width":45,"y":340,"height":42},{"name":"ziyuan/masak14","x":344,"width":31,"y":261,"height":33},{"name":"ziyuan/masak15","x":344,"width":21,"y":330,"height":21},{"name":"ziyuan/fk1","x":344,"width":31,"y":296,"height":32},{"name":"ziyuan/fk2","x":0,"width":52,"y":388,"height":52},{"name":"ziyuan/fk3","x":367,"width":94,"y":340,"height":94},{"name":"ziyuan/fk4","x":397,"width":110,"y":113,"height":110},{"name":"ziyuan/fk5","x":123,"width":116,"y":261,"height":108}],"imagePath":"texture.png"}