{"frameRate":24,"name":"shandian","armature":[{"name":"shandian","bone":[{"transform":{"skX":0,"scY":1,"x":111.1,"skY":0,"y":-1.5,"scX":0.97},"name":"shandian_01"},{"transform":{"skX":0,"scY":1,"x":111.35,"skY":0,"y":0.5,"scX":0.97},"name":"shandian_02"},{"transform":{"skX":0,"scY":1,"x":114.25,"skY":0,"y":2,"scX":0.97},"name":"shandian_03"},{"transform":{"skX":0,"scY":1,"x":115.05,"skY":0,"y":2.7,"scX":0.97},"name":"shandian_04"}],"skin":[{"slot":[{"name":"shandian_01","z":0,"display":[{"transform":{"pY":49,"scY":1,"x":125,"y":24.5,"skX":0,"skY":0,"pX":250,"scX":1},"name":"yuanjian/shandian_01","type":"image"}],"parent":"shandian_01"},{"name":"shandian_02","z":1,"display":[{"transform":{"pY":39,"scY":1,"x":119.55,"y":19.5,"skX":0,"skY":0,"pX":239,"scX":1},"name":"yuanjian/shandian_02","type":"image"}],"parent":"shandian_02"},{"name":"shandian_03","z":2,"display":[{"transform":{"pY":39,"scY":1,"x":119.55,"y":19.5,"skX":0,"skY":0,"pX":239,"scX":1},"name":"yuanjian/shandian_03","type":"image"}],"parent":"shandian_03"},{"name":"shandian_04","z":3,"display":[{"transform":{"pY":38,"scY":1,"x":121.45,"y":19,"skX":0,"skY":0,"pX":243,"scX":1},"name":"yuanjian/shandian_04","type":"image"}],"parent":"shandian_04"}],"name":"default"}],"animation":[{"autoTween":1,"timeline":[{"name":"shandian_01","scale":1,"frame":[{"transform":{"pY":0,"scY":1,"x":111.1,"y":-1.5,"skX":0,"skY":0,"pX":0,"scX":0.97},"z":0,"duration":2},{"duration":6,"displayIndex":-1}],"offset":0},{"name":"shandian_02","scale":1,"frame":[{"duration":2,"displayIndex":-1},{"transform":{"pY":0,"scY":1,"x":111.35,"y":0.5,"skX":0,"skY":0,"pX":0,"scX":0.97},"z":1,"duration":2},{"duration":4,"displayIndex":-1}],"offset":0},{"name":"shandian_03","scale":1,"frame":[{"duration":4,"displayIndex":-1},{"transform":{"pY":0,"scY":1,"x":114.25,"y":2,"skX":0,"skY":0,"pX":0,"scX":0.97},"z":2,"duration":2},{"duration":2,"displayIndex":-1}],"offset":0},{"name":"shandian_04","scale":1,"frame":[{"duration":6,"displayIndex":-1},{"transform":{"pY":0,"scY":1,"x":115.05,"y":2.7,"skX":0,"skY":0,"pX":0,"scX":0.97},"z":3,"duration":2}],"offset":0}],"duration":8,"scale":1,"loop":1,"tweenEasing":null,"name":"shandian","fadeInTime":0.3}]}],"version":2.3}